<?SCHEMA schemaVersion="1.0"?>
<SignalSourcesConfiguration xmlns:xsi="http://www.w3.org/2001/XMLSchema-instance" xsi:noNamespaceSchemaLocation="file:///C:/Program%20Files%20(x86)/Common%20Files/ETAS/Experiment%20Environment/3.7/Schemas/EE.Data.SignalSources.xsd" xsi:type="ETAS.EE.Data.SignalSourcesConfigurationType">
  <SignalSourcesData xsi:type="ETAS.EE.Data.PluginDataListType">
    <Item xsi:type="ETAS.EE.Data.PluginDataType" id="ID0f9c46ac-b15c-465c-8008-0b7061b49ec9" pluginID="System" rootFolder="System_Files">
      <Documents xsi:type="ETAS.EE.Data.ExternalDocumentListType">
        <Item xsi:type="ETAS.EE.Data.ExternalDocumentType" id="IDfc104036-cfdf-4953-b3d5-f5d33bf4a40d" type="" name="Configuration" file="Configuration.xml" />
      </Documents>
    </Item>
  </SignalSourcesData>
  <SignalSourceDeclarations xsi:type="ETAS.EE.Data.SignalSourceDeclarationListType">
    <Item xsi:type="ETAS.EE.Data.SignalSourceDeclarationType" id="ID3cd93dbb-ad5b-49ce-b30e-d2004f7f8ddc" type="VP" signalSourceId="System" name="randomtest_PC" active="true" />
  </SignalSourceDeclarations>
</SignalSourcesConfiguration>